messaging_client
