Metadata-Version: 1.1
Name: AaronOS-Messaging
Version: 0.1.1
Summary: A command line client for the messaging app in Aaron OS
Home-page: https://github.com/edison-moreland/AaronOS-Messaging-Client
Author: Edison Moreland
Author-email: edison@devdude.net
License: MIT
Download-URL: https://github.com/edison-moreland/AaronOS-Messaging-Client/archive/0.1.1.tar.gz
Platform: UNKNOWN
